{
  "id": "slabs.theme.halloween-pumpkin-night",
  "name": "Halloween Pumpkin Night (Editor theme)",
  "main": "dist/main.js",
  "version": "1.0.0",
  "readme": "README.md",
  "icon": "icon.png",
  "files": [],
  "minVersionCode": 292,
  "price": 0,
  "license": "MIT",
  "keywords": ["AMOLED","OLED", "Dark", "Black", "Theme"],
  "changelogs": "CHANGELOGS.md",
  "author": {
    "name": "ScriptLabs",
    "email": "scriptlabsmc@gmail.com",
    "url": "https://scriptlabsmc.vercel.app",
    "github": "ScriptLabsMC"
  }
}